otaku_watcher_contrib/__init__.py
otaku_watcher_contrib/animepahe.py
otaku_watcher_contrib/anitaku.py
otaku_watcher_contrib/hianime.py
otaku_watcher_contrib/kisskh.py
otaku_watcher_contrib/tokyo_insider.py
otaku_watcher_contrib-1.2.10.dist-info/licenses/LICENSE
otaku_watcher_contrib-1.2.10.dist-info/METADATA
otaku_watcher_contrib-1.2.10.dist-info/WHEEL
otaku_watcher_contrib-1.2.10.dist-info/top_level.txt
otaku_watcher_contrib-1.2.10.dist-info/RECORD
