Metadata-Version: 2.4
Name: otaku-watcher-contrib
Version: 1.2.10
Summary: A mov-cli plugin for watching anime and more!
License:             DO WHAT THE FUCK YOU WANT TO PUBLIC LICENSE
Project-URL: GitHub, https://github.com/GDjkhp/otaku-watcher-contrib
Project-URL: BugTracker, https://github.com/GDjkhp/otaku-watcher-contrib/issues
Keywords: mov-cli,animepahe,kisskh,anime,🐔👔
Classifier: Operating System :: Microsoft :: Windows :: Windows 11
Classifier: Operating System :: Microsoft :: Windows :: Windows 10
Classifier: Operating System :: POSIX :: Linux
Classifier: License :: OSI Approved :: MIT License
Classifier: Programming Language :: Python :: 3.8
Classifier: Programming Language :: Python :: 3.9
Classifier: Programming Language :: Python :: 3.10
Classifier: Programming Language :: Python :: 3.11
Requires-Python: >=3.8
License-File: LICENSE
Requires-Dist: requests
Requires-Dist: importlib-metadata; python_version < "3.8"
Requires-Dist: mov-cli>=4.4
Requires-Dist: thefuzz
Requires-Dist: quickjs
Provides-Extra: dev
Requires-Dist: ruff; extra == "dev"
Requires-Dist: build; extra == "dev"
Dynamic: license-file
